charmcraftst124/__init__.py
charmcraftst124/main.py
charmcraftst124-0.1.10.dist-info/METADATA
charmcraftst124-0.1.10.dist-info/WHEEL
charmcraftst124-0.1.10.dist-info/entry_points.txt
charmcraftst124-0.1.10.dist-info/RECORD
