Metadata-Version: 2.3
Name: charmcraftst124
Version: 0.1.10
Summary: (deprecated) Temporary compatibility wrapper to use ST124 shorthand notation with older versions of charmcraft 3 that don't support ST124
Author: Carl Csaposs
Author-email: carl.csaposs@canonical.com
Requires-Python: >=3.10
Classifier: Programming Language :: Python :: 3
Classifier: Programming Language :: Python :: 3.10
Classifier: Programming Language :: Python :: 3.11
Classifier: Programming Language :: Python :: 3.12
Classifier: Programming Language :: Python :: 3.13
Requires-Dist: packaging (>=24.2,<25.0)
Requires-Dist: pyyaml (>=6.0.2,<7.0.0)
Requires-Dist: requests (>=2.32.3,<3.0.0)
Requires-Dist: typer (>=0.15.0,<0.16.0)
Requires-Dist: typing-extensions (>=4.12.2,<5.0.0)
